{"name": "P250 | 红岩 ", "wear": 0.0424465611577034, "price": 78.39, "itemset": "九头蛇大行动", "time": "2024-03-25,02:14:49"}
{"name": "P250 | 红岩 ", "wear": 0.04653216525912285, "price": 78.0, "itemset": "九头蛇大行动", "time": "2024-03-25,02:14:49"}
{"name": "P250 | 红岩 ", "wear": 0.05838968604803085, "price": 77.99, "itemset": "九头蛇大行动", "time": "2024-03-25,02:14:49"}
{"name": "P250 | 红岩 ", "wear": 0.11541612446308136, "price": 58.46, "itemset": "九头蛇大行动", "time": "2024-03-25,02:14:49"}
{"name": "P250 | 红岩 ", "wear": 0.14081820845603943, "price": 58.57, "itemset": "九头蛇大行动", "time": "2024-03-25,02:14:49"}
{"name": "P250 | 红岩 ", "wear": 0.14486268162727356, "price": 58.56, "itemset": "九头蛇大行动", "time": "2024-03-25,02:14:49"}
