{"name": "P250 | 卡特尔 ", "wear": 0.06303409487009048, "price": 90.0, "itemset": "先锋", "time": "2024-03-25,01:54:53"}
{"name": "P250 | 卡特尔 ", "wear": 0.06882702559232712, "price": 90.0, "itemset": "先锋", "time": "2024-03-25,01:54:53"}
{"name": "P250 | 卡特尔 ", "wear": 0.06891264021396637, "price": 90.0, "itemset": "先锋", "time": "2024-03-25,01:54:53"}
{"name": "P250 | 卡特尔 ", "wear": 0.14603736996650696, "price": 42.0, "itemset": "先锋", "time": "2024-03-25,01:55:00"}
{"name": "P250 | 卡特尔 ", "wear": 0.14640530943870544, "price": 40.27, "itemset": "先锋", "time": "2024-03-25,01:55:00"}
{"name": "P250 | 卡特尔 ", "wear": 0.14816907048225403, "price": 40.28, "itemset": "先锋", "time": "2024-03-25,01:55:00"}
