{"name": "MP5-SD | 越野 ", "wear": 0.06506920605897903, "price": 0.39, "itemset": "2018炼狱小镇", "time": "2024-03-25,02:13:05"}
{"name": "MP5-SD | 越野 ", "wear": 0.06825752556324005, "price": 0.38, "itemset": "2018炼狱小镇", "time": "2024-03-25,02:13:05"}
{"name": "MP5-SD | 越野 ", "wear": 0.06983017921447754, "price": 0.4, "itemset": "2018炼狱小镇", "time": "2024-03-25,02:13:05"}
{"name": "MP5-SD | 越野 ", "wear": 0.11090214550495148, "price": 0.1, "itemset": "2018炼狱小镇", "time": "2024-03-25,02:13:04"}
{"name": "MP5-SD | 越野 ", "wear": 0.12792068719863892, "price": 0.09, "itemset": "2018炼狱小镇", "time": "2024-03-25,02:13:04"}
{"name": "MP5-SD | 越野 ", "wear": 0.13242584466934204, "price": 0.1, "itemset": "2018炼狱小镇", "time": "2024-03-25,02:13:04"}
