{"name": "Tec-9 | 碎蛋白石 ", "wear": 0.051630690693855286, "price": 2.28, "itemset": "光谱2号", "time": "2024-03-25,00:41:27"}
{"name": "Tec-9 | 碎蛋白石 ", "wear": 0.052223991602659225, "price": 2.38, "itemset": "光谱2号", "time": "2024-03-25,00:41:27"}
{"name": "Tec-9 | 碎蛋白石 ", "wear": 0.05514730140566826, "price": 2.29, "itemset": "光谱2号", "time": "2024-03-25,00:41:27"}
{"name": "Tec-9 | 碎蛋白石 ", "wear": 0.13112394511699677, "price": 0.96, "itemset": "光谱2号", "time": "2024-03-25,00:41:27"}
{"name": "Tec-9 | 碎蛋白石 ", "wear": 0.13435855507850647, "price": 0.98, "itemset": "光谱2号", "time": "2024-03-25,00:41:27"}
{"name": "Tec-9 | 碎蛋白石 ", "wear": 0.14212638139724731, "price": 0.97, "itemset": "光谱2号", "time": "2024-03-25,00:41:27"}
{"name": "Tec-9 | 碎蛋白石 ", "wear": 0.24950453639030457, "price": 0.8, "itemset": "光谱2号", "time": "2024-03-25,00:41:27"}
{"name": "Tec-9 | 碎蛋白石 ", "wear": 0.2529855966567993, "price": 0.79, "itemset": "光谱2号", "time": "2024-03-25,00:41:27"}
{"name": "Tec-9 | 碎蛋白石 ", "wear": 0.3096975088119507, "price": 0.87, "itemset": "光谱2号", "time": "2024-03-25,00:41:27"}
