{"name": "SG 553 | 豹灯蛾 ", "wear": 0.06675116717815399, "price": 15.5, "itemset": "左轮武器箱", "time": "2024-03-25,01:26:55"}
{"name": "SG 553 | 豹灯蛾 ", "wear": 0.06839169561862946, "price": 15.5, "itemset": "左轮武器箱", "time": "2024-03-25,01:26:55"}
{"name": "SG 553 | 豹灯蛾 ", "wear": 0.06976253539323807, "price": 15.59, "itemset": "左轮武器箱", "time": "2024-03-25,01:26:55"}
{"name": "SG 553 | 豹灯蛾 ", "wear": 0.14206074178218842, "price": 7.27, "itemset": "左轮武器箱", "time": "2024-03-25,01:26:48"}
{"name": "SG 553 | 豹灯蛾 ", "wear": 0.142801433801651, "price": 6.96, "itemset": "左轮武器箱", "time": "2024-03-25,01:26:48"}
{"name": "SG 553 | 豹灯蛾 ", "wear": 0.14881539344787598, "price": 6.96, "itemset": "左轮武器箱", "time": "2024-03-25,01:26:48"}
{"name": "SG 553 | 豹灯蛾 ", "wear": 0.3291316032409668, "price": 4.75, "itemset": "左轮武器箱", "time": "2024-03-25,01:26:55"}
{"name": "SG 553 | 豹灯蛾 ", "wear": 0.34521159529685974, "price": 4.76, "itemset": "左轮武器箱", "time": "2024-03-25,01:26:55"}
{"name": "SG 553 | 豹灯蛾 ", "wear": 0.3549991548061371, "price": 4.76, "itemset": "左轮武器箱", "time": "2024-03-25,01:26:55"}
