{"name": "截短霰弹枪 | 贤者涂装 ", "wear": 0.1344747394323349, "price": 10.79, "itemset": "死亡游乐园", "time": "2024-03-25,01:20:09"}
{"name": "截短霰弹枪 | 贤者涂装 ", "wear": 0.14357715845108032, "price": 10.79, "itemset": "死亡游乐园", "time": "2024-03-25,01:20:09"}
{"name": "截短霰弹枪 | 贤者涂装 ", "wear": 0.14712785184383392, "price": 10.79, "itemset": "死亡游乐园", "time": "2024-03-25,01:20:09"}
{"name": "截短霰弹枪 | 贤者涂装 ", "wear": 0.2084372341632843, "price": 2.99, "itemset": "死亡游乐园", "time": "2024-03-25,01:20:02"}
{"name": "截短霰弹枪 | 贤者涂装 ", "wear": 0.2646956443786621, "price": 2.99, "itemset": "死亡游乐园", "time": "2024-03-25,01:20:02"}
{"name": "截短霰弹枪 | 贤者涂装 ", "wear": 0.28951823711395264, "price": 3.02, "itemset": "死亡游乐园", "time": "2024-03-25,01:20:02"}
