{"name": "G3SG1 | 净化者 ", "wear": 0.05571262538433075, "price": 10.09, "itemset": "头号特训", "time": "2024-03-25,02:01:03"}
{"name": "G3SG1 | 净化者 ", "wear": 0.06499739736318588, "price": 10.08, "itemset": "头号特训", "time": "2024-03-25,02:01:03"}
{"name": "G3SG1 | 净化者 ", "wear": 0.06935139745473862, "price": 10.26, "itemset": "头号特训", "time": "2024-03-25,02:01:03"}
{"name": "G3SG1 | 净化者 ", "wear": 0.13103201985359192, "price": 5.34, "itemset": "头号特训", "time": "2024-03-25,02:01:03"}
{"name": "G3SG1 | 净化者 ", "wear": 0.1406346708536148, "price": 5.36, "itemset": "头号特训", "time": "2024-03-25,02:01:03"}
{"name": "G3SG1 | 净化者 ", "wear": 0.1414213627576828, "price": 5.33, "itemset": "头号特训", "time": "2024-03-25,02:01:03"}
{"name": "G3SG1 | 净化者 ", "wear": 0.25578269362449646, "price": 3.29, "itemset": "头号特训", "time": "2024-03-25,02:01:03"}
{"name": "G3SG1 | 净化者 ", "wear": 0.27612635493278503, "price": 3.36, "itemset": "头号特训", "time": "2024-03-25,02:01:03"}
{"name": "G3SG1 | 净化者 ", "wear": 0.2883445918560028, "price": 3.3, "itemset": "头号特训", "time": "2024-03-25,02:01:03"}
