{"name": "双持贝瑞塔 | 蔷薇 ", "wear": 0.02714616246521473, "price": 38.29, "itemset": "古堡激战", "time": "2024-03-25,01:17:17"}
{"name": "双持贝瑞塔 | 蔷薇 ", "wear": 0.05099710077047348, "price": 38.28, "itemset": "古堡激战", "time": "2024-03-25,01:17:17"}
{"name": "双持贝瑞塔 | 蔷薇 ", "wear": 0.06753703206777573, "price": 38.28, "itemset": "古堡激战", "time": "2024-03-25,01:17:17"}
{"name": "双持贝瑞塔 | 蔷薇 ", "wear": 0.11268270015716553, "price": 23.66, "itemset": "古堡激战", "time": "2024-03-25,01:17:08"}
{"name": "双持贝瑞塔 | 蔷薇 ", "wear": 0.11629100143909454, "price": 23.76, "itemset": "古堡激战", "time": "2024-03-25,01:17:08"}
{"name": "双持贝瑞塔 | 蔷薇 ", "wear": 0.14958281815052032, "price": 23.43, "itemset": "古堡激战", "time": "2024-03-25,01:17:08"}
